insightface/__init__.py
insightface/app/__init__.py
insightface/app/face_analysis.py
insightface/model_zoo/__init__.py
insightface/model_zoo/face_detection.py
insightface/model_zoo/face_genderage.py
insightface/model_zoo/face_recognition.py
insightface/model_zoo/model_store.py
insightface/model_zoo/model_zoo.py
insightface/utils/__init__.py
insightface/utils/download.py
insightface/utils/face_align.py
insightface/utils/filesystem.py
insightface1-0.1.5.dist-info/DESCRIPTION.rst
insightface1-0.1.5.dist-info/METADATA
insightface1-0.1.5.dist-info/RECORD
insightface1-0.1.5.dist-info/WHEEL
insightface1-0.1.5.dist-info/metadata.json
insightface1-0.1.5.dist-info/top_level.txt
insightface1-0.1.5.dist-info/zip-safe
