Metadata-Version: 2.0
Name: insightface1
Version: 0.1.5
Summary: InsightFace Toolkit
Home-page: https://github.com/deepinsight/insightface
Author: InsightFace Contributors
Author-email: UNKNOWN
License: Apache-2.0
Platform: UNKNOWN
Requires-Dist: Pillow
Requires-Dist: easydict
Requires-Dist: matplotlib
Requires-Dist: numpy
Requires-Dist: opencv-python
Requires-Dist: requests
Requires-Dist: scikit-image
Requires-Dist: scikit-learn
Requires-Dist: scipy
Requires-Dist: tqdm
